pillar_queue/__init__.py
pillar_queue/client.py
pillar_queue/test_client.py
pillar_queue_wrapper-0.0.1.dist-info/LICENSE
pillar_queue_wrapper-0.0.1.dist-info/METADATA
pillar_queue_wrapper-0.0.1.dist-info/WHEEL
pillar_queue_wrapper-0.0.1.dist-info/top_level.txt
pillar_queue_wrapper-0.0.1.dist-info/RECORD
