Metadata-Version: 2.1
Name: pillar-queue-wrapper
Version: 0.0.1
Summary: Our internal queue wrapper.
Home-page: https://github.com/pillargg/pillar-queue-wrapper
Author: Pillar
Author-email: opensource@pillar.gg
License: UNKNOWN
Platform: UNKNOWN
Classifier: Programming Language :: Python :: 3
Classifier: License :: OSI Approved :: MIT License
Classifier: Operating System :: OS Independent
Requires-Python: >=3.6
Requires-Dist: boto3 (>=1.17.8)
